CHANGES.txt
DESC.txt
MANIFEST.in
README.md
setup.py
OutputCatcher.egg-info/PKG-INFO
OutputCatcher.egg-info/SOURCES.txt
OutputCatcher.egg-info/dependency_links.txt
OutputCatcher.egg-info/top_level.txt
docs/README.rst
outputcatcher/__init__.py
outputcatcher/__main__.py
outputcatcher/catchers.py
test/__init__.py
test/processoutput_test_helper.py
test/test_outputcatcher.py