Metadata-Version: 1.1
Name: OutputCatcher
Version: 0.0.9
Summary: Catches/silences stdout/stderr output.
